grow/__init__.py
grow/__main__.py
grow/cli.py
grow/cache/__init__.py
grow/cache/collection_cache.py
grow/cache/collection_cache_test.py
grow/cache/document_cache.py
grow/cache/document_cache_test.py
grow/cache/file_cache.py
grow/cache/file_cache_test.py
grow/cache/object_cache.py
grow/cache/object_cache_test.py
grow/cache/podcache.py
grow/cache/podcache_test.py
grow/cache/routes_cache.py
grow/cache/routes_cache_test.py
grow/collections/__init__.py
grow/collections/collection.py
grow/collections/collection_routes.py
grow/collections/collection_test.py
grow/commands/__init__.py
grow/commands/deprecated.py
grow/commands/group.py
grow/commands/shared.py
grow/commands/subcommands/__init__.py
grow/commands/subcommands/build.py
grow/commands/subcommands/convert.py
grow/commands/subcommands/deploy.py
grow/commands/subcommands/inspect.py
grow/commands/subcommands/inspect_routes.py
grow/commands/subcommands/inspect_stats.py
grow/commands/subcommands/inspect_untranslated.py
grow/commands/subcommands/install.py
grow/commands/subcommands/preprocess.py
grow/commands/subcommands/run.py
grow/commands/subcommands/stage.py
grow/commands/subcommands/translations.py
grow/commands/subcommands/translations_diff.py
grow/commands/subcommands/translations_download.py
grow/commands/subcommands/translations_extract.py
grow/commands/subcommands/translations_extract_test.py
grow/commands/subcommands/translations_filter.py
grow/commands/subcommands/translations_filter_test.py
grow/commands/subcommands/translations_import.py
grow/commands/subcommands/translations_import_test.py
grow/commands/subcommands/translations_upload.py
grow/common/__init__.py
grow/common/base_config.py
grow/common/base_config_test.py
grow/common/bulk_errors.py
grow/common/colors.py
grow/common/colors_test.py
grow/common/deprecated.py
grow/common/deprecated_test.py
grow/common/features.py
grow/common/features_test.py
grow/common/json_encoder.py
grow/common/json_encoder_test.py
grow/common/logger.py
grow-2.2.3.dist-info/LICENSE
grow-2.2.3.dist-info/METADATA
grow-2.2.3.dist-info/WHEEL
grow-2.2.3.dist-info/entry_points.txt
grow-2.2.3.dist-info/top_level.txt
grow-2.2.3.dist-info/RECORD
